djangocms_inherit/__init__.py
djangocms_inherit/cms_plugins.py
djangocms_inherit/forms.py
djangocms_inherit/models.py
djangocms_inherit/locale/af/LC_MESSAGES/django.mo
djangocms_inherit/locale/af/LC_MESSAGES/django.po
djangocms_inherit/locale/ar/LC_MESSAGES/django.mo
djangocms_inherit/locale/ar/LC_MESSAGES/django.po
djangocms_inherit/locale/be/LC_MESSAGES/django.mo
djangocms_inherit/locale/be/LC_MESSAGES/django.po
djangocms_inherit/locale/bg/LC_MESSAGES/django.mo
djangocms_inherit/locale/bg/LC_MESSAGES/django.po
djangocms_inherit/locale/bn/LC_MESSAGES/django.mo
djangocms_inherit/locale/bn/LC_MESSAGES/django.po
djangocms_inherit/locale/ca/LC_MESSAGES/django.mo
djangocms_inherit/locale/ca/LC_MESSAGES/django.po
djangocms_inherit/locale/cmn/LC_MESSAGES/django.mo
djangocms_inherit/locale/cmn/LC_MESSAGES/django.po
djangocms_inherit/locale/cs/LC_MESSAGES/django.mo
djangocms_inherit/locale/cs/LC_MESSAGES/django.po
djangocms_inherit/locale/cy/LC_MESSAGES/django.mo
djangocms_inherit/locale/cy/LC_MESSAGES/django.po
djangocms_inherit/locale/da/LC_MESSAGES/django.mo
djangocms_inherit/locale/da/LC_MESSAGES/django.po
djangocms_inherit/locale/de/LC_MESSAGES/django.mo
djangocms_inherit/locale/de/LC_MESSAGES/django.po
djangocms_inherit/locale/el/LC_MESSAGES/django.mo
djangocms_inherit/locale/el/LC_MESSAGES/django.po
djangocms_inherit/locale/en/LC_MESSAGES/django.mo
djangocms_inherit/locale/en/LC_MESSAGES/django.po
djangocms_inherit/locale/es/LC_MESSAGES/django.mo
djangocms_inherit/locale/es/LC_MESSAGES/django.po
djangocms_inherit/locale/es_AR/LC_MESSAGES/django.mo
djangocms_inherit/locale/es_AR/LC_MESSAGES/django.po
djangocms_inherit/locale/es_BO/LC_MESSAGES/django.mo
djangocms_inherit/locale/es_BO/LC_MESSAGES/django.po
djangocms_inherit/locale/es_DO/LC_MESSAGES/django.mo
djangocms_inherit/locale/es_DO/LC_MESSAGES/django.po
djangocms_inherit/locale/et/LC_MESSAGES/django.mo
djangocms_inherit/locale/et/LC_MESSAGES/django.po
djangocms_inherit-0.2.2.dist-info/DESCRIPTION.rst
djangocms_inherit-0.2.2.dist-info/METADATA
djangocms_inherit-0.2.2.dist-info/RECORD
djangocms_inherit-0.2.2.dist-info/WHEEL
djangocms_inherit-0.2.2.dist-info/metadata.json
djangocms_inherit-0.2.2.dist-info/top_level.txt
